ShimlaMqttClient/InternetConnection.py
ShimlaMqttClient/MqttBrokerConnection.py
ShimlaMqttClient/ShimlaMysqlDB.py
ShimlaMqttClient/__init__.py
shimlamqttclientlib-1.0.8.dist-info/LICENSE.txt
shimlamqttclientlib-1.0.8.dist-info/METADATA
shimlamqttclientlib-1.0.8.dist-info/WHEEL
shimlamqttclientlib-1.0.8.dist-info/top_level.txt
shimlamqttclientlib-1.0.8.dist-info/RECORD
