Metadata-Version: 2.1
Name: shimlamqttclientlib
Version: 1.0.8
Summary: SHIMLA MQTT Client Library
Home-page: UNKNOWN
Author: Sivakumar Venkatesan
Author-email: siva@infiswift.tech
License: UNKNOWN
Keywords: mqtt client library
Platform: UNKNOWN
Classifier: Development Status :: 3 - Alpha
Classifier: Intended Audience :: Developers
Classifier: Topic :: Software Development :: Build Tools
Classifier: License :: OSI Approved :: MIT License
Classifier: Programming Language :: Python :: 3
Classifier: Programming Language :: Python :: 3.4
Classifier: Programming Language :: Python :: 3.5
Classifier: Programming Language :: Python :: 3.6
Classifier: Programming Language :: Python :: 3.7
